Workbook

Sheet 00_Read Me
A1: Hotel Operational Excellence & Profitability Case Study
A3: Purpose | B3: Formula-driven portfolio case study covering P&L, PVM, labour variance, scenarios, returns, sensitivity, benefits tracking and executive communication.
A4: Inputs | B4: Blue font and yellow fill.
A5: Formula cells | B5: Black font.
A6: Cross-sheet links | B6: Green font.
A7: Variance convention | B7: Positive denotes favourable to GOP; negative denotes unfavourable.
A8: Case status | B8: Independent synthetic case study for professional development; no employer or Mandarin Oriental data.
A9: Open in Excel | B9: Workbook is configured for automatic full recalculation.
A12: Verification Summary
A13: Check | B13: Expected | C13: Workbook Formula | D13: Status | E13: Explanation
A14: PVM reconciliation | B14: 0 | C14: ='03_PVM Bridge'!B20 -> 0 | D14: =IF(ABS(C14-B14)<0.01,"PASS","FAIL") -> PASS | E14: Bridge effects reconcile budget to actual rooms revenue.
A15: Labour reconciliation | B15: 0 | C15: ='04_Labour Variance'!D16 -> 0 | D15: =IF(ABS(C15-B15)<0.01,"PASS","FAIL") -> PASS | E15: Component effects reconcile to total P&L labour variance.

Sheet 01_Inputs KPIs
A1: 01. Single-Source Inputs and KPIs
A5: Metric | B5: Units | C5: Budget | D5: Actual | E5: Latest Forecast | F5: Actual vs Budget | G5: Forecast vs Budget | H5: Definition
A6: Physical rooms | B6: rooms | C6: 305 | D6: 305 | E6: 305 | F6: =D6-C6 -> 0 | G6: =E6-C6 -> 0 | H6: Building inventory
A7: Out-of-order rooms | B7: rooms | C7: 5 | D7: 5 | E7: 5 | F7: =D7-C7 -> 0 | G7: =E7-C7 -> 0 | H7: Unavailable rooms
A8: Days | B8: days | C8: 30 | D8: 30 | E8: 30 | F8: =D8-C8 -> 0 | G8: =E8-C8 -> 0 | H8: Days in period
A9: Available room nights | B9: room nights | C9: =(C6-C7)*C8 -> 9000 | D9: =(D6-D7)*D8 -> 9000 | E9: =(E6-E7)*E8 -> 9000 | F9: =D9-C9 -> 0 | G9: =E9-C9 -> 0 | H9: Net available rooms × days
A10: Rooms sold | B10: room nights | C10: 7200 | D10: 7350 | E10: 7470 | F10: =D10-C10 -> 150 | G10: =E10-C10 -> 270 | H10: Paid room nights
A11: Rooms revenue | B11: HK$ | C11: 18000000 | D11: 17640000 | E11: 18110520 | F11: =D11-C11 -> -360000 | G11: =E11-C11 -> 110520 | H11: Rooms revenue
A12: F&B revenue | B12: HK$ | C12: 8000000 | D12: 8400000 | E12: 8620000 | F12: =D12-C12 -> 400000 | G12: =E12-C12 -> 620000 | H12: Food and beverage revenue
A13: Other revenue | B13: HK$ | C13: 2000000 | D13: 1900000 | E13: 1950000 | F13: =D13-C13 -> -100000 | G13: =E13-C13 -> -50000 | H13: Other operated departments
A14: Core hours | B14: hours | C14: 170000 | D14: 174000 | E14: 172000 | F14: =D14-C14 -> 4000 | G14: =E14-C14 -> 2000 | H14: Core labour hours
A15: Base rate | B15: HK$/hour | C15: 40 | D15: 41 | E15: 41 | F15: =D15-C15 -> 1 | G15: =E15-C15 -> 1 | H15: Average base hourly rate
A16: OT hours | B16: hours | C16: 2000 | D16: 3400 | E16: 2900 | F16: =D16-C16 -> 1400 | G16: =E16-C16 -> 900 | H16: Overtime hours
A17: OT premium | B17: HK$/hour | C17: 20 | D17: 22 | E17: 22 | F17: =D17-C17 -> 2 | G17: =E17-C17 -> 2 | H17: Incremental premium rate
A18: Agency hours | B18: hours | C18: 10000 | D18: 15200 | E18: 12500 | F18: =D18-C18 -> 5200 | G18: =E18-C18 -> 2500 | H18: Agency hours
A19: Agency rate | B19: HK$/hour | C19: 50 | D19: 60 | E19: 58 | F19: =D19-C19 -> 10 | G19: =E19-C19 -> 8 | H19: Loaded agency rate
A20: Other labour | B20: HK$ | C20: 1060000 | D20: 1119200 | E20: 1090000 | F20: =D20-C20 -> 59200 | G20: =E20-C20 -> 30000 | H20: Other payroll and benefits
A21: F&B cost | B21: HK$ | C21: 2560000 | D21: 2940000 | E21: 2887700 | F21: =D21-C21 -> 380000 | G21: =E21-C21 -> 327700 | H21: Direct F&B cost
... A24: Guest satisfaction | B24: score | C24: 90 | D24: 88 | E24: 89 | F24: =D24-C24 -> -2 | G24: =E24-C24 -> -1 | H24: Service guardrail
A27: Calculated KPIs
A28: KPI | B28: Units | C28: Budget | D28: Actual | E28: Latest Forecast | F28: Actual vs Budget | G28: Forecast vs Budget | H28: Interpretation
A29: Occupancy | B29: % | C29: =C10/C9 -> 0.8 | D29: =D10/D9 -> 0.81666667 | E29: =E10/E9 -> 0.83 | F29: =D29-C29 -> 0.016666667 | G29: =E29-C29 -> 0.03 | H29: Rooms sold / available room nights
A30: ADR | B30: HK$ | C30: =C11/C10 -> 2500 | D30: =D11/D10 -> 2400 | E30: =E11/E10 -> 2424.4337 | F30: =D30-C30 -> -100 | G30: =E30-C30 -> -75.566265 | H30: Rooms revenue / rooms sold
A31: RevPAR | B31: HK$ | C31: =C11/C9 -> 2000 | D31: =D11/D9 -> 1960 | E31: =E11/E9 -> 2012.28 | F31: =D31-C31 -> -40 | G31: =E31-C31 -> 12.28 | H31: Rooms revenue / available room nights
A32: F&B cost % | B32: % | C32: =C21/C12 -> 0.32 | D32: =D21/D12 -> 0.35 | E32: =E21/E12 -> 0.335 | F32: =D32-C32 -> 0.03 | G32: =E32-C32 -> 0.015 | H32: F&B cost / F&B revenue
A33: Labour cost | B33: HK$ | C33: =C14*C15+C16*C17+C18*C19+C20 -> 8400000 | D33: =D14*D15+D16*D17+D18*D19+D20 -> 9240000 | E33: =E14*E15+E16*E17+E18*E19+E20 -> 8930800 | F33: =D33-C33 -> 840000 | G33: =E33-C33 -> 530800 | H33: Core + OT premium + agency + other labour
A34: Total revenue | B34: HK$ | C34: =SUM(C11:C13) -> 28000000 | D34: =SUM(D11:D13) -> 27940000 | E34: =SUM(E11:E13) -> 28680520 | F34: =D34-C34 -> -60000 | G34: =E34-C34 -> 680520 | H34: Revenue total
A35: Total operating cost | B35: HK$ | C35: =SUM(C33,C21:C23) -> 17200000 | D35: =SUM(D33,D21:D23) -> 18640000 | E35: =SUM(E33,E21:E23) -> 18178500 | F35: =D35-C35 -> 1440000 | G35: =E35-C35 -> 978500 | H35: Labour + other costs
A36: GOP | B36: HK$ | C36: =C34-C35 -> 10800000 | D36: =D34-D35 -> 9300000 | E36: =E34-E35 -> 10502020 | F36: =D36-C36 -> -1500000 | G36: =E36-C36 -> -297980 | H36: Revenue - operating costs
A37: GOP margin | B37: % | C37: =C36/C34 -> 0.38571429 | D37: =D36/D34 -> 0.33285612 | E37: =E36/E34 -> 0.36617258 | F37: =D37-C37 -> -0.052858165 | G37: =E37-C37 -> -0.019541706 | H37: GOP / revenue
A38: GOPPAR | B38: HK$ | C38: =C36/C9 -> 1200 | D38: =D36/D9 -> 1033.3333 | E38: =E36/E9 -> 1166.8911 | F38: =D38-C38 -> -166.66667 | G38: =E38-C38 -> -33.108889 | H38: GOP / available room nights

Sheet 02_P&L Variance
A1: 02. Integrated P&L and Variance
A5: P&L Line | B5: Category | C5: Budget | D5: Actual | E5: Forecast | F5: Actual Var F/(U) | G5: Var % | H5: Forecast Var F/(U) | I5: Driver | J5: Commentary
A6: Rooms revenue | B6: Revenue | C6: ='01_Inputs KPIs'!C11 -> 18000000 | D6: ='01_Inputs KPIs'!D11 -> 17640000 | E6: ='01_Inputs KPIs'!E11 -> 18110520 | F6: =D6-C6 -> -360000 | G6: =IFERROR(F6/ABS(C6),0) -> -0.02 | H6: =E6-C6 -> 110520 | I6: Volume, mix, rate | J6: Use PVM bridge.
A7: F&B revenue | B7: Revenue | C7: ='01_Inputs KPIs'!C12 -> 8000000 | D7: ='01_Inputs KPIs'!D12 -> 8400000 | E7: ='01_Inputs KPIs'!E12 -> 8620000 | F7: =D7-C7 -> 400000 | G7: =IFERROR(F7/ABS(C7),0) -> 0.05 | H7: =E7-C7 -> 620000
A8: Other revenue | B8: Revenue | C8: ='01_Inputs KPIs'!C13 -> 2000000 | D8: ='01_Inputs KPIs'!D13 -> 1900000 | E8: ='01_Inputs KPIs'!E13 -> 1950000 | F8: =D8-C8 -> -100000 | G8: =IFERROR(F8/ABS(C8),0) -> -0.05 | H8: =E8-C8 -> -50000
A10: Total revenue | B10: RevenueTotal | C10: =SUM(C6:C8) -> 28000000 | D10: =SUM(D6:D8) -> 27940000 | E10: =SUM(E6:E8) -> 28680520 | F10: =D10-C10 -> -60000 | G10: =IFERROR(F10/ABS(C10),0) -> -0.0021428571 | H10: =E10-C10 -> 680520
A12: Core labour | B12: CostFormula | C12: ='01_Inputs KPIs'!C14*'01_Inputs KPIs'!C15 -> 6800000 | D12: ='01_Inputs KPIs'!D14*'01_Inputs KPIs'!D15 -> 7134000 | E12: ='01_Inputs KPIs'!E14*'01_Inputs KPIs'!E15 -> 7052000 | F12: =C12-D12 -> -334000 | G12: =IFERROR(F12/ABS(C12),0) -> -0.049117647 | H12: =C12-E12 -> -252000
A13: OT premium | B13: CostFormula | C13: ='01_Inputs KPIs'!C16*'01_Inputs KPIs'!C17 -> 40000 | D13: ='01_Inputs KPIs'!D16*'01_Inputs KPIs'!D17 -> 74800 | E13: ='01_Inputs KPIs'!E16*'01_Inputs KPIs'!E17 -> 63800 | F13: =C13-D13 -> -34800 | G13: =IFERROR(F13/ABS(C13),0) -> -0.87 | H13: =C13-E13 -> -23800
A14: Agency labour | B14: CostFormula | C14: ='01_Inputs KPIs'!C18*'01_Inputs KPIs'!C19 -> 500000 | D14: ='01_Inputs KPIs'!D18*'01_Inputs KPIs'!D19 -> 912000 | E14: ='01_Inputs KPIs'!E18*'01_Inputs KPIs'!E19 -> 725000 | F14: =C14-D14 -> -412000 | G14: =IFERROR(F14/ABS(C14),0) -> -0.824 | H14: =C14-E14 -> -225000
A15: Other labour | B15: Cost | C15: ='01_Inputs KPIs'!C20 -> 1060000 | D15: ='01_Inputs KPIs'!D20 -> 1119200 | E15: ='01_Inputs KPIs'!E20 -> 1090000 | F15: =C15-D15 -> -59200 | G15: =IFERROR(F15/ABS(C15),0) -> -0.055849057 | H15: =C15-E15 -> -30000
A16: Total labour | B16: CostTotal | C16: =SUM(C12:C15) -> 8400000 | D16: =SUM(D12:D15) -> 9240000 | E16: =SUM(E12:E15) -> 8930800 | F16: =C16-D16 -> -840000 | G16: =IFERROR(F16/ABS(C16),0) -> -0.1 | H16: =C16-E16 -> -530800 | I16: Hours and rates | J16: Use labour bridge.
A18: F&B cost | B18: Cost | C18: ='01_Inputs KPIs'!C21 -> 2560000 | D18: ='01_Inputs KPIs'!D21 -> 2940000 | E18: ='01_Inputs KPIs'!E21 -> 2887700 | F18: =C18-D18 -> -380000 | G18: =IFERROR(F18/ABS(C18),0) -> -0.1484375 | H18: =C18-E18 -> -327700 | I18: Price, mix, waste | J18: Review F&B cost percentage.
A19: Utilities | B19: Cost | C19: ='01_Inputs KPIs'!C22 -> 1200000 | D19: ='01_Inputs KPIs'!D22 -> 1300000 | E19: ='01_Inputs KPIs'!E22 -> 1270000 | F19: =C19-D19 -> -100000 | G19: =IFERROR(F19/ABS(C19),0) -> -0.083333333 | H19: =C19-E19 -> -70000
A20: Other opex | B20: Cost | C20: ='01_Inputs KPIs'!C23 -> 5040000 | D20: ='01_Inputs KPIs'!D23 -> 5160000 | E20: ='01_Inputs KPIs'!E23 -> 5090000 | F20: =C20-D20 -> -120000 | G20: =IFERROR(F20/ABS(C20),0) -> -0.023809524 | H20: =C20-E20 -> -50000
A22: Total operating cost | B22: CostTotal | C22: =SUM(C16,C18:C20) -> 17200000 | D22: =SUM(D16,D18:D20) -> 18640000 | E22: =SUM(E16,E18:E20) -> 18178500 | F22: =C22-D22 -> -1440000 | G22: =IFERROR(F22/ABS(C22),0) -> -0.08372093 | H22: =C22-E22 -> -978500
A24: GOP | B24: Profit | C24: =C10-C22 -> 10800000 | D24: =D10-D22 -> 9300000 | E24: =E10-E22 -> 10502020 | F24: =D24-C24 -> -1500000 | G24: =IFERROR(F24/ABS(C24),0) -> -0.13888889 | H24: =E24-C24 -> -297980
A25: GOP margin | B25: Margin | C25: =C24/C10 -> 0.38571429 | D25: =D24/D10 -> 0.33285612 | E25: =E24/E10 -> 0.36617258 | F25: =D25-C25 -> -0.052858165 | G25: =IFERROR(F25/ABS(C25),0) -> -0.13703969 | H25: =E25-C25 -> -0.019541706
A26: GOPPAR | B26: Profit | C26: =C24/'01_Inputs KPIs'!C9 -> 1200 | D26: =D24/'01_Inputs KPIs'!D9 -> 1033.3333 | E26: =E24/'01_Inputs KPIs'!E9 -> 1166.8911 | F26: =D26-C26 -> -166.66667 | G26: =IFERROR(F26/ABS(C26),0) -> -0.13888889 | H26: =E26-C26 -> -33.108889

Sheet 03_PVM Bridge
A1: 03. Segment Price-Volume-Mix Bridge
A3: Volume uses budget weighted ADR; mix uses budget segment ADR; rate uses actual segment volume.
A5: Segment | B5: Budget Rooms | C5: Budget ADR | D5: Budget Revenue | E5: Budget Mix | F5: Actual Rooms | G5: Actual ADR | H5: Actual Revenue | I5: Actual Mix | J5: Volume Effect | K5: Mix Effect | L5: Rate Effect
A6: Corporate | B6: 2880 | C6: 2200 | D6: =B6*C6 -> 6336000 | E6: =B6/$B$9 -> 0.4 | F6: 3300 | G6: 2150 | H6: =F6*G6 -> 7095000 | I6: =F6/$F$9 -> 0.44897959 | J6: =($F$9-$B$9)*$C$9*E6 -> 150000 | K6: =($I6-$E6)*$F$9*C6 -> 792000 | L6: =F6*(G6-C6) -> -165000
A7: Leisure | B7: 2880 | C7: 2600 | D7: =B7*C7 -> 7488000 | E7: =B7/$B$9 -> 0.4 | F7: 2800 | G7: 2550 | H7: =F7*G7 -> 7140000 | I7: =F7/$F$9 -> 0.38095238 | J7: =($F$9-$B$9)*$C$9*E7 -> 150000 | K7: =($I7-$E7)*$F$9*C7 -> -364000 | L7: =F7*(G7-C7) -> -140000
A8: Group | B8: 1440 | C8: 2900 | D8: =B8*C8 -> 4176000 | E8: =B8/$B$9 -> 0.2 | F8: 1250 | G8: 2724 | H8: =F8*G8 -> 3405000 | I8: =F8/$F$9 -> 0.17006803 | J8: =($F$9-$B$9)*$C$9*E8 -> 75000 | K8: =($I8-$E8)*$F$9*C8 -> -638000 | L8: =F8*(G8-C8) -> -220000
A9: Total / weighted | B9: =SUM(B6:B8) -> 7200 | C9: =D9/B9 -> 2500 | D9: =SUM(D6:D8) -> 18000000 | E9: =SUM(E6:E8) -> 1 | F9: =SUM(F6:F8) -> 7350 | G9: =H9/F9 -> 2400 | H9: =SUM(H6:H8) -> 17640000 | I9: =SUM(I6:I8) -> 1 | J9: =SUM(J6:J8) -> 375000 | K9: =SUM(K6:K8) -> -210000 | L9: =SUM(L6:L8) -> -525000
A12: Reconciliation
A13: Budget revenue | B13: =D9 -> 18000000
A14: Volume effect | B14: =J9 -> 375000
A15: Mix effect | B15: =K9 -> -210000
A16: Rate effect | B16: =L9 -> -525000
A17: Explained actual revenue | B17: =SUM(B13:B16) -> 17640000
A18: Reported actual revenue | B18: =H9 -> 17640000
A19: Reconciliation Check | B19: =B17-B18 -> 0
A20: P&L rooms revenue check | B20: =H9-'02_P&L Variance'!D6 -> 0

Sheet 04_Labour Variance
A1: 04. Labour Quantity and Rate Bridge
A3: Positive = favourable to GOP; negative = adverse.
A5: Component | B5: Budget Qty | C5: Budget Rate | D5: Budget Cost | E5: Actual Qty | F5: Actual Rate | G5: Actual Cost | H5: Quantity Effect | I5: Rate Effect | J5: Total Effect
A6: Core labour | B6: 170000 | C6: 40 | D6: =B6*C6 -> 6800000 | E6: 174000 | F6: 41 | G6: =E6*F6 -> 7134000 | H6: =-(E6-B6)*C6 -> -160000 | I6: =-(F6-C6)*E6 -> -174000 | J6: =H6+I6 -> -334000
A7: OT premium | B7: 2000 | C7: 20 | D7: =B7*C7 -> 40000 | E7: 3400 | F7: 22 | G7: =E7*F7 -> 74800 | H7: =-(E7-B7)*C7 -> -28000 | I7: =-(F7-C7)*E7 -> -6800 | J7: =H7+I7 -> -34800
A8: Agency labour | B8: 10000 | C8: 50 | D8: =B8*C8 -> 500000 | E8: 15200 | F8: 60 | G8: =E8*F8 -> 912000 | H8: =-(E8-B8)*C8 -> -260000 | I8: =-(F8-C8)*E8 -> -152000 | J8: =H8+I8 -> -412000
A10: Other labour | D10: 1060000 | G10: 1119200 | J10: =D10-G10 -> -59200
A12: Total labour | D12: =SUM(D6:D8,D10) -> 8400000 | G12: =SUM(G6:G8,G10) -> 9240000 | J12: =SUM(J6:J8,J10) -> -840000
A14: P&L labour F/(U) | D14: ='02_P&L Variance'!F16 -> -840000
A15: Bridge total F/(U) | D15: =J12 -> -840000
A16: Reconciliation Check | D16: =D15-D14 -> 0

Sheet 05_Scenarios
A1: 05. Driver-Based Scenarios
A5: Driver / Output | B5: Units | C5: Current Actual | D5: Base | E5: Moderate | F5: Stretch | G5: Rationale | H5: Decision Note
A6: Available room nights | B6: room nights | C6: 9000 | D6: 9000 | E6: 9000 | F6: 9000 | G6: Editable scenario driver
A7: Occupancy | B7: % | C7: 0.81666667 | D7: 0.815 | E7: 0.82 | F7: 0.825 | G7: Editable scenario driver
A8: ADR | B8: HK$ | C8: 2400 | D8: 2400 | E8: 2430 | F8: 2470 | G8: Editable scenario driver
A9: F&B revenue | B9: HK$ | C9: 8400000 | D9: 8450000 | E9: 8600000 | F9: 8750000 | G9: Editable scenario driver
A10: Other revenue | B10: HK$ | C10: 1900000 | D10: 1900000 | E10: 1950000 | F10: 2000000 | G10: Editable scenario driver
A11: Core hours | B11: hours | C11: 174000 | D11: 174000 | E11: 171000 | F11: 168000 | G11: Editable scenario driver
A12: Base rate | B12: HK$/hour | C12: 41 | D12: 41 | E12: 41 | F12: 41 | G12: Editable scenario driver
A13: OT hours | B13: hours | C13: 3400 | D13: 3300 | E13: 2890 | F13: 2380 | G13: Editable scenario driver
A14: OT premium | B14: HK$/hour | C14: 22 | D14: 22 | E14: 22 | F14: 22 | G14: Editable scenario driver
A15: Agency hours | B15: hours | C15: 15200 | D15: 15000 | E15: 12160 | F15: 9880 | G15: Editable scenario driver
A16: Agency rate | B16: HK$/hour | C16: 60 | D16: 60 | E16: 58 | F16: 56 | G16: Editable scenario driver
A17: Other labour | B17: HK$ | C17: 1119200 | D17: 1119200 | E17: 1090000 | F17: 1060000 | G17: Editable scenario driver
... A24: Guardrail threshold | B24: score | C24: 88 | D24: 88 | E24: 88 | F24: 88 | G24: Editable scenario driver
A27: Calculated Outputs
A28: Rooms sold | C28: =C6*C7 -> 7350 | D28: =D6*D7 -> 7335 | E28: =E6*E7 -> 7380 | F28: =F6*F7 -> 7425
A29: Rooms revenue | C29: =C28*C8 -> 17640000 | D29: =D28*D8 -> 17604000 | E29: =E28*E8 -> 17933400 | F29: =F28*F8 -> 18339750
A30: Total revenue | C30: =SUM(C29,C9,C10) -> 27940000 | D30: =SUM(D29,D9,D10) -> 27954000 | E30: =SUM(E29,E9,E10) -> 28483400 | F30: =SUM(F29,F9,F10) -> 29089750
A31: Core labour | C31: =C11*C12 -> 7134000 | D31: =D11*D12 -> 7134000 | E31: =E11*E12 -> 7011000 | F31: =F11*F12 -> 6888000
A32: OT premium | C32: =C13*C14 -> 74800 | D32: =D13*D14 -> 72600 | E32: =E13*E14 -> 63580 | F32: =F13*F14 -> 52360
A33: Agency labour | C33: =C15*C16 -> 912000 | D33: =D15*D16 -> 900000 | E33: =E15*E16 -> 705280 | F33: =F15*F16 -> 553280
A34: Total labour | C34: =SUM(C31:C33,C17) -> 9240000 | D34: =SUM(D31:D33,D17) -> 9225800 | E34: =SUM(E31:E33,E17) -> 8869860 | F34: =SUM(F31:F33,F17) -> 8553640
A35: F&B cost | C35: =C9*C18 -> 2940000 | D35: =D9*D18 -> 2957500 | E35: =E9*E18 -> 2881000 | F35: =F9*F18 -> 2843750
A36: Total operating cost | C36: =SUM(C34,C35,C19,C20) -> 18640000 | D36: =SUM(D34,D35,D19,D20) -> 18673300 | E36: =SUM(E34,E35,E19,E20) -> 18110860 | F36: =SUM(F34,F35,F19,F20) -> 17647390
A37: GOP | C37: =C30-C36 -> 9300000 | D37: =D30-D36 -> 9280700 | E37: =E30-E36 -> 10372540 | F37: =F30-F36 -> 11442360
A38: GOP margin | C38: =C37/C30 -> 0.33285612 | D38: =D37/D30 -> 0.331999 | E38: =E37/E30 -> 0.36416088 | F38: =F37/F30 -> 0.3933468
A39: GOPPAR | C39: =C37/C6 -> 1033.3333 | D39: =D37/D6 -> 1031.1889 | E39: =E37/E6 -> 1152.5044 | F39: =F37/F6 -> 1271.3733
A40: Monthly GOP uplift vs Base | C40: =0 -> 0 | D40: =0 -> 0 | E40: =E37-$D$37 -> 1091840 | F40: =F37-$D$37 -> 2161660
A41: Annual gross benefit vs Base | C41: =0 -> 0 | D41: =0 -> 0 | E41: =E40*12 -> 13102080 | F41: =F40*12 -> 25939920
A42: Annual net benefit | C42: =0 -> 0 | D42: =0 -> 0 | E42: =E41-E21 -> 12302080 | F42: =F41-F21 -> 24339920
A43: Risk-adjusted net benefit | C43: =0 -> 0 | D43: =0 -> 0 | E43: =E42*E23 -> 9226560 | F43: =F42*F23 -> 14603952
A44: Guardrail status | C44: =IF(C22>=C24,"PASS","FAIL") -> PASS | D44: =IF(D22>=D24,"PASS","FAIL") -> PASS | E44: =IF(E22>=E24,"PASS","FAIL") -> PASS | F44: =IF(F22>=F24,"PASS","FAIL") -> FAIL

Sheet 06_Returns Sensitivity
A1: 06. Returns and Sensitivity Analysis
A5: Metric | B5: Base | C5: Moderate | D5: Stretch | E5: Formula / Logic | F5: Decision Use | G5: Validation | H5: Owner | I5: Status | J5: Low Case | K5: High Case
A6: Annual gross benefit | B6: ='05_Scenarios'!D41 -> 0 | C6: ='05_Scenarios'!E41 -> 13102080 | D6: ='05_Scenarios'!F41 -> 25939920 | E6: Monthly GOP uplift × 12
A7: Implementation cost | B7: ='05_Scenarios'!D21 -> 0 | C7: ='05_Scenarios'!E21 -> 800000 | D7: ='05_Scenarios'!F21 -> 1600000 | E7: One-off investment
A8: Annual net benefit | B8: ='05_Scenarios'!D42 -> 0 | C8: ='05_Scenarios'!E42 -> 12302080 | D8: ='05_Scenarios'!F42 -> 24339920 | E8: Gross benefit - implementation cost
A9: ROI | B9: =IFERROR(B8/B7,0) -> 0 | C9: =IFERROR(C8/C7,0) -> 15.3776 | D9: =IFERROR(D8/D7,0) -> 15.21245 | E9: Net benefit / investment
A10: Monthly net benefit | B10: =B8/12 -> 0 | C10: =C8/12 -> 1025173.3 | D10: =D8/12 -> 2028326.7 | E10: Annual net / 12
A11: Payback | B11: =IFERROR(B7/B10,0) -> 0 | C11: =IFERROR(C7/C10,0) -> 0.78035584 | D11: =IFERROR(D7/D10,0) -> 0.78882757 | E11: Investment / monthly net
A12: Discount rate | B12: 0.08 | C12: 0.08 | D12: 0.08 | E12: Editable discount rate
A13: Year 1 factor | B13: 0.75 | C13: 0.75 | D13: 0.75 | E13: Ramp-up
A14: Year 2 factor | B14: 1 | C14: 1 | D14: 1 | E14: Steady state
A15: Year 3 factor | B15: 0.9 | C15: 0.9 | D15: 0.9 | E15: Sustainability/leakage
A16: Year 1 cash flow | B16: =B8*B13 -> 0 | C16: =C8*C13 -> 9226560 | D16: =D8*D13 -> 18254940 | E16: Annual net × Y1 factor
A17: Year 2 cash flow | B17: =B8*B14 -> 0 | C17: =C8*C14 -> 12302080 | D17: =D8*D14 -> 24339920 | E17: Annual net × Y2 factor
A18: Year 3 cash flow | B18: =B8*B15 -> 0 | C18: =C8*C15 -> 11071872 | D18: =D8*D15 -> 21905928 | E18: Annual net × Y3 factor
A19: NPV | B19: =NPV(B12,B16:B18)-B7 -> 0 | C19: =NPV(C12,C16:C18)-C7 -> 27079371 | D19: =NPV(D12,D16:D18)-D7 -> 53559912 | E19: PV cash flows - investment
A20: Risk-adjusted annual net benefit | B20: ='05_Scenarios'!D43 -> 0 | C20: ='05_Scenarios'!E43 -> 9226560 | D20: ='05_Scenarios'!F43 -> 14603952 | E20: Annual net × confidence
A23: Moderate Scenario: Confidence Sensitivity
A24: Metric | B24: 0.5 | C24: 0.6 | D24: 0.7 | E24: 0.75 | F24: 0.8 | G24: 0.9 | H24: 1
A25: Risk-adjusted annual net benefit | B25: ='05_Scenarios'!E42*B24 -> 6151040 | C25: ='05_Scenarios'!E42*C24 -> 7381248 | D25: ='05_Scenarios'!E42*D24 -> 8611456 | E25: ='05_Scenarios'!E42*E24 -> 9226560 | F25: ='05_Scenarios'!E42*F24 -> 9841664 | G25: ='05_Scenarios'!E42*G24 -> 11071872 | H25: ='05_Scenarios'!E42*H24 -> 12302080
A28: Moderate Scenario: Implementation Cost Sensitivity
A29: Metric | B29: -0.2 | C29: -0.1 | D29: 0 | E29: 0.1 | F29: 0.2
A30: Implementation cost | B30: ='05_Scenarios'!E21*(1+B29) -> 640000 | C30: ='05_Scenarios'!E21*(1+C29) -> 720000 | D30: ='05_Scenarios'!E21*(1+D29) -> 800000 | E30: ='05_Scenarios'!E21*(1+E29) -> 880000 | F30: ='05_Scenarios'!E21*(1+F29) -> 960000
A31: Annual net benefit | B31: ='05_Scenarios'!E41-B30 -> 12462080 | C31: ='05_Scenarios'!E41-C30 -> 12382080 | D31: ='05_Scenarios'!E41-D30 -> 12302080 | E31: ='05_Scenarios'!E41-E30 -> 12222080 | F31: ='05_Scenarios'!E41-F30 -> 12142080
A32: ROI | B32: =IFERROR(B31/B30,0) -> 19.472 | C32: =IFERROR(C31/C30,0) -> 17.197333 | D32: =IFERROR(D31/D30,0) -> 15.3776 | E32: =IFERROR(E31/E30,0) -> 13.888727 | F32: =IFERROR(F31/F30,0) -> 12.648
A33: Payback | B33: =IFERROR(B30/(B31/12),0) -> 0.61626952 | C33: =IFERROR(C30/(C31/12),0) -> 0.6977826 | D33: =IFERROR(D30/(D31/12),0) -> 0.78035584 | E33: =IFERROR(E30/(E31/12),0) -> 0.86401005 | F33: =IFERROR(F30/(F31/12),0) -> 0.9487666
A36: Moderate Scenario: Two-Way Risk-Adjusted Net Benefit
A37: Benefit achievement → / Cost overrun ↓ | B37: 0.6 | C37: 0.7 | D37: 0.8 | E37: 0.9 | F37: 1
A38: -0.1 | B38: =('05_Scenarios'!E41*B$37-'05_Scenarios'!E21*(1+$A38))*'05_Scenarios'!E23 -> 5355936 | C38: =('05_Scenarios'!E41*C$37-'05_Scenarios'!E21*(1+$A38))*'05_Scenarios'!E23 -> 6338592 | D38: =('05_Scenarios'!E41*D$37-'05_Scenarios'!E21*(1+$A38))*'05_Scenarios'!E23 -> 7321248 | E38: =('05_Scenarios'!E41*E$37-'05_Scenarios'!E21*(1+$A38))*'05_Scenarios'!E23 -> 8303904 | F38: =('05_Scenarios'!E41*F$37-'05_Scenarios'!E21*(1+$A38))*'05_Scenarios'!E23 -> 9286560
A39: 0 | B39: =('05_Scenarios'!E41*B$37-'05_Scenarios'!E21*(1+$A39))*'05_Scenarios'!E23 -> 5295936 | C39: =('05_Scenarios'!E41*C$37-'05_Scenarios'!E21*(1+$A39))*'05_Scenarios'!E23 -> 6278592 | D39: =('05_Scenarios'!E41*D$37-'05_Scenarios'!E21*(1+$A39))*'05_Scenarios'!E23 -> 7261248 | E39: =('05_Scenarios'!E41*E$37-'05_Scenarios'!E21*(1+$A39))*'05_Scenarios'!E23 -> 8243904 | F39: =('05_Scenarios'!E41*F$37-'05_Scenarios'!E21*(1+$A39))*'05_Scenarios'!E23 -> 9226560
A40: 0.1 | B40: =('05_Scenarios'!E41*B$37-'05_Scenarios'!E21*(1+$A40))*'05_Scenarios'!E23 -> 5235936 | C40: =('05_Scenarios'!E41*C$37-'05_Scenarios'!E21*(1+$A40))*'05_Scenarios'!E23 -> 6218592 | D40: =('05_Scenarios'!E41*D$37-'05_Scenarios'!E21*(1+$A40))*'05_Scenarios'!E23 -> 7201248 | E40: =('05_Scenarios'!E41*E$37-'05_Scenarios'!E21*(1+$A40))*'05_Scenarios'!E23 -> 8183904 | F40: =('05_Scenarios'!E41*F$37-'05_Scenarios'!E21*(1+$A40))*'05_Scenarios'!E23 -> 9166560
A41: 0.2 | B41: =('05_Scenarios'!E41*B$37-'05_Scenarios'!E21*(1+$A41))*'05_Scenarios'!E23 -> 5175936 | C41: =('05_Scenarios'!E41*C$37-'05_Scenarios'!E21*(1+$A41))*'05_Scenarios'!E23 -> 6158592 | D41: =('05_Scenarios'!E41*D$37-'05_Scenarios'!E21*(1+$A41))*'05_Scenarios'!E23 -> 7141248 | E41: =('05_Scenarios'!E41*E$37-'05_Scenarios'!E21*(1+$A41))*'05_Scenarios'!E23 -> 8123904 | F41: =('05_Scenarios'!E41*F$37-'05_Scenarios'!E21*(1+$A41))*'05_Scenarios'!E23 -> 9106560
A42: 0.3 | B42: =('05_Scenarios'!E41*B$37-'05_Scenarios'!E21*(1+$A42))*'05_Scenarios'!E23 -> 5115936 | C42: =('05_Scenarios'!E41*C$37-'05_Scenarios'!E21*(1+$A42))*'05_Scenarios'!E23 -> 6098592 | D42: =('05_Scenarios'!E41*D$37-'05_Scenarios'!E21*(1+$A42))*'05_Scenarios'!E23 -> 7081248 | E42: =('05_Scenarios'!E41*E$37-'05_Scenarios'!E21*(1+$A42))*'05_Scenarios'!E23 -> 8063904 | F42: =('05_Scenarios'!E41*F$37-'05_Scenarios'!E21*(1+$A42))*'05_Scenarios'!E23 -> 9046560
A44: Interpretation | B44: Use one-way tables to isolate confidence and implementation-cost effects. Use the two-way table to test simultaneous benefit under-delivery and cost overrun. Reject scenarios that fail service guardrails even if financial returns remain positive.

Sheet 07_Benefits Tracker
A1: 07. Benefits Validation Tracker
A5: ID | B5: Opportunity | C5: Type | D5: Baseline Method | E5: Business Owner | F5: Finance Validator | G5: Forecast Gross | H5: Implementation Cost | I5: Forecast Net | J5: Realised | K5: Volume/Seasonality Adj. | L5: Attribution % | M5: Adjusted Benefit | N5: Validated Benefit | O5: Guardrail | P5: Sustainability | Q5: Status | R5: Evidence
A6: B-001 | B6: Moderate hotel profitability pilot | C6: Recurring cost reduction / revenue uplift | D6: Base counterfactual plus agreed normalisation | E6: Hotel Operations Lead | F6: Property Finance Lead | G6: ='05_Scenarios'!E41 -> 13102080 | H6: ='05_Scenarios'!E21 -> 800000 | I6: ='05_Scenarios'!E42 -> 12302080 | J6: 0 | K6: 0 | L6: 0.75 | M6: =(J6-K6)*L6 -> 0 | N6: 0 | O6: Guest satisfaction >= 88 | P6: Month 3 and 6 | Q6: Forecast | R6: Actual realised and validated values remain zero until evidence and Finance sign-off.

Sheet 08_Executive Summary
A1: 08. Executive Summary and Decision Request
A3: Headline
A4: Near-budget revenue is not converting to planned GOP. Labour and F&B costs require a controlled Moderate pilot with Finance validation and service guardrails.
A6: What happened?
A7: Revenue Actual | B7: ='02_P&L Variance'!D10 -> 27940000 | C7: F/(U) | D7: ='02_P&L Variance'!F10 -> -60000
A8: GOP Actual | B8: ='02_P&L Variance'!D24 -> 9300000 | C8: F/(U) | D8: ='02_P&L Variance'!F24 -> -1500000
A10: Why does it matter?
A11: GOP margin | B11: ='02_P&L Variance'!D25 -> 0.33285612 | C11: Budget | D11: ='02_P&L Variance'!C25 -> 0.38571429
A12: Guest satisfaction | B12: ='01_Inputs KPIs'!D24 -> 88 | C12: Guardrail | D12: ='05_Scenarios'!E24 -> 88
A14: What is causing it?
A15: 1. PVM bridge identifies volume, mix and rate drivers.
A16: 2. Labour bridge isolates hours and rate effects across core, OT and agency.
A17: 3. F&B cost percentage is above budget.
A19: What should we do?
A20: 1. Validate source data and baselines.
A21: 2. Pilot Moderate scenario in two departments.
A22: 3. Monitor guest and operating guardrails.
A24: Financial impact
A25: Moderate annual net | B25: ='05_Scenarios'!E42 -> 12302080 | C25: Risk-adjusted | D25: ='05_Scenarios'!E43 -> 9226560
A26: ROI | B26: ='06_Returns Sensitivity'!C9 -> 15.3776 | C26: Payback | D26: ='06_Returns Sensitivity'!C11 -> 0.78035584
A27: NPV | B27: ='06_Returns Sensitivity'!C19 -> 27079371 | C27: Guardrail | D27: ='05_Scenarios'!E44 -> PASS
A30: Decision required
A31: Approve the Moderate pilot; confirm Business and Finance owners; endorse baseline, attribution and double-count controls; and stop or redesign the pilot if service guardrails are breached.

Sheet 09_Formula Guide
A1: 09. Formula and Link Guide
A4: Area | B4: Formula | C4: Meaning | D4: Cross-Sheet Source | E4: Validation | F4: Interview Language
A5: Occupancy | B5: Rooms sold / available room nights | C5: Capacity utilisation | D5: 01 Inputs | E5: Confirm unavailable rooms | F5: Occupancy improved, but I assess it with ADR and profit.
A6: PVM volume | B6: (Actual total rooms - Budget total rooms) × Budget weighted ADR | C6: Demand effect | D6: 03 PVM | E6: Bridge to actual revenue | F6: Volume was favourable.
A7: PVM mix | B7: Σ[(Actual mix-Budget mix)×Actual total rooms×Budget segment ADR] | C7: Segment mix effect | D7: 03 PVM | E7: Stable segment definitions | F7: Mix changed revenue independent of total demand.
A8: PVM rate | B8: Σ[Actual rooms×(Actual ADR-Budget ADR)] | C8: Achieved-rate effect | D8: 03 PVM | E8: Contract/channel review | F8: Rate pressure outweighed volume.
A9: Labour quantity | B9: -(Actual qty-Budget qty)×Budget rate | C9: Hours effect | D9: 04 Labour | E9: Normalise for actual demand | F9: I test labour hours against demand and service standards.
A10: Labour rate | B10: -(Actual rate-Budget rate)×Actual qty | C10: Rate effect | D10: 04 Labour | E10: Payroll/invoice reconciliation | F10: I isolate contractual and agency-rate effects.
A11: Annual net | B11: Monthly GOP uplift×12 - implementation cost | C11: Value after investment | D11: 05 Scenarios | E11: Same period and ramp-up | F11: I compare net, not gross, value.
A12: ROI | B12: Annual net / implementation cost | C12: Return multiple | D12: 06 Returns | E12: Period consistency | F12: The option returns X per dollar invested.
A13: Payback | B13: Implementation cost / monthly net benefit | C13: Recovery period | D13: 06 Returns | E13: Ramp-up timing | F13: The investment recovers in X months.
A14: NPV | B14: PV of forecast cash flows - initial investment | C14: Time-adjusted value | D14: 06 Returns | E14: Discount rate and timing | F14: NPV tests whether future benefits justify the investment.
A15: Validated benefit | B15: (Realised-adjustments)×attribution, Finance approved | C15: Credible benefit | D15: 07 Tracker | E15: Baseline, seasonality, double counting | F15: I distinguish forecast, realised, validated and sustained benefits.
